<?xml version="1.0" encoding="utf-8"?>
<tv>
  <channel id="LA 1">
    <display-name lang="es">La 1</display-name>
    <url>http://www.plus.es</url>
  </channel>
  <channel id="LA 2">
    <display-name lang="es">La 2</display-name>
    <url>http://www.plus.es</url>
  </channel>
  <channel id="Antena 3">
    <display-name lang="es">antena 3</display-name>
    <url>http://www.plus.es</url>
  </channel>
  <channel id="Neox">
    <display-name lang="es">neox</display-name>
    <url>http://www.plus.es</url>
  </channel>
  <channel id="La Sexta">
    <display-name lang="es">La Sexta</display-name>
    <url>http://www.plus.es</url>
  </channel>
  <channel id="Nova">
    <display-name lang="es">nova</display-name>
    <url>http://www.plus.es</url>
  </channel>
  <channel id="Mega">
    <display-name lang="es">mega</display-name>
    <url>http://www.plus.es</url>
  </channel>
  <channel id="Factoría de Ficción">
    <display-name lang="es">FDF</display-name>
    <url>http://www.plus.es</url>
  </channel>
  <channel id="Paramount Channel">
    <display-name lang="es">PARAMOUNT CHANNEL</display-name>
    <url>http://www.plus.es</url>
  </channel>
  <channel id="Boing">
    <display-name lang="es">Boing</display-name>
    <url>http://www.plus.es</url>
  </channel>
  <channel id="Cuatro">
    <display-name lang="es">Cuatro</display-name>
    <url>http://www.plus.es</url>
  </channel>
  <channel id="Atreseries">
    <display-name lang="es">atreseries</display-name>
    <url>http://www.plus.es</url>
  </channel>
  <channel id="Telecinco">
    <display-name lang="es">Telecinco</display-name>
    <url>http://www.plus.es</url>
  </channel>
  <channel id="Divinity">
    <display-name lang="es">Divinity</display-name>
    <url>http://www.plus.es</url>
  </channel>
  <channel id="Energy">
    <display-name lang="es">Energy</display-name>
    <url>http://www.plus.es</url>
  </channel>
  <channel id="BE MAD">
    <display-name lang="es">BeMad tv</display-name>
    <url>http://www.plus.es</url>
  </channel>
  <channel id="13 TV">
    <display-name lang="es">TRECE</display-name>
    <url>http://www.plus.es</url>
  </channel>
  <channel id="Real Madrid TV">
    <display-name lang="es">Realmadrid TV</display-name>
    <url>http://www.plus.es</url>
  </channel>
  <channel id="Canal Sur Andalucía">
    <display-name lang="es">Canal Sur Andalucía</display-name>
    <url>http://www.plus.es</url>
  </channel>
  <channel id="Aragón TV Int">
    <display-name lang="es">Aragón TV Int</display-name>
    <url>http://www.plus.es</url>
  </channel>
  <channel id="TPA">
    <display-name lang="es">TPA</display-name>
    <url>http://www.plus.es</url>
  </channel>
  <channel id="IB3 RTV Illes Balears">
    <display-name lang="es">IB3 RTV Illes Balears</display-name>
    <url>http://www.plus.es</url>
  </channel>
  <channel id="TelevisiónCanaria">
    <display-name lang="es">TelevisiónCanaria</display-name>
    <url>http://www.plus.es</url>
  </channel>
  <channel id="TV3 Cat">
    <display-name lang="es">TV3 Cat</display-name>
    <url>http://www.plus.es</url>
  </channel>
  <channel id="3 24">
    <display-name lang="es">3 24</display-name>
    <url>http://www.plus.es</url>
  </channel>
  <channel id="7TVMUR">
    <display-name lang="es">7TVMUR</display-name>
    <url>http://www.plus.es</url>
  </channel>
  <channel id="24 Horas">
    <display-name lang="es">24h</display-name>
    <url>http://www.plus.es</url>
  </channel>
  <channel id="EXTRE">
    <display-name lang="es">EXTRE</display-name>
    <url>http://www.plus.es</url>
  </channel>
</tv>
